[
  {
    "comments": [
      {
        "line": 1,
        "value": "#language: pt"
      },
      {
        "line": 2,
        "value": "#Author: Klaus Merini"
      },
      {
        "line": 3,
        "value": "#Version: 1.0"
      },
      {
        "line": 4,
        "value": "#Encoding: UTF-8"
      }
    ],
    "line": 7,
    "elements": [
      {
        "before": [
          {
            "result": {
              "duration": 2232471900,
              "status": "passed"
            },
            "match": {
              "location": "Hooks.beforeScenario(Scenario)"
            }
          }
        ],
        "line": 39,
        "name": "Comprar de todos menus",
        "description": "",
        "id": "comprar-livro;comprar-de-todos-menus",
        "after": [
          {
            "result": {
              "duration": 1083260900,
              "status": "passed"
            },
            "match": {
              "location": "Hooks.afterScenario(Scenario)"
            }
          }
        ],
        "type": "scenario",
        "keyword": "Cenario",
        "steps": [
          {
            "result": {
              "duration": 12227343400,
              "status": "passed"
            },
            "line": 40,
            "name": "que estou no site demowebshop",
            "match": {
              "location": "CompraLivroSteps.que_estou_no_site_demowebshop()"
            },
            "keyword": "Dado "
          },
          {
            "result": {
              "duration": 46164744500,
              "status": "passed"
            },
            "line": 41,
            "name": "clico em cada menu selecionando todos produtos de cada menu",
            "match": {
              "location": "CompraLivroSteps.clicoEmCadaMenuSelecionandoTodosProdutosDeCadaMenu()"
            },
            "keyword": "E "
          },
          {
            "result": {
              "duration": 1560405300,
              "status": "passed"
            },
            "line": 42,
            "name": "site adiciona os produtos (todos) ao carrinho de compras",
            "match": {
              "location": "CompraLivroSteps.siteAdicionaOsProdutosTodosAoCarrinhoDeCompras()"
            },
            "keyword": "Entao "
          }
        ],
        "tags": [
          {
            "line": 38,
            "name": "@compratudo"
          }
        ]
      }
    ],
    "name": "Comprar livro",
    "description": "",
    "id": "comprar-livro",
    "keyword": "Funcionalidade",
    "uri": "carrinho.feature",
    "tags": [
      {
        "line": 6,
        "name": "@funcionalidades"
      }
    ]
  }
]